{"ab":"abkhazo","af":"afrikaans","ak":"ak\u00e1n","am":"am\u00e1rico","an":"aragon\u00e9s","ar":"\u00e1rabe","as":"assam\u00e9s","ay":"aimar\u00e1","az":"azer\u00ed","ba":"baskir","be":"bielorruso","bg":"b\u00falgaro","bm":"bambara","bn":"bengal\u00ed","bo":"tibetano","br":"bret\u00f3n","bs":"bosnio","ca":"catal\u00e1n","co":"corso","cs":"checo","cu":"eslavo eclesi\u00e1stico","cy":"gal\u00e9s","da":"dinamarqu\u00e9s","de":"alem\u00e1n","de_AT":"alem\u00e1n de austria","de_CH":"alto alem\u00e1n su\u00edzo","dv":"divehi","dz":"dzongkha","ee":"ew\u00e9","el":"grego","en":"ingl\u00e9s","en_AU":"ingl\u00e9s australiano","en_CA":"ingl\u00e9s canadiano","en_GB":"ingl\u00e9s R.U.","en_US":"ingl\u00e9s EUA","eo":"esperanto","es":"espa\u00f1ol","es_ES":"castel\u00e1n","es_MX":"espa\u00f1ol de M\u00e9xico","et":"estoniano","eu":"\u00e9uscaro","fa":"persa","fi":"fin\u00e9s","fj":"fixiano","fo":"faro\u00e9s","fr":"franc\u00e9s","fr_CA":"franc\u00e9s canadiano","fr_CH":"franc\u00e9s su\u00edzo","fy":"fris\u00f3n","ga":"irland\u00e9s","gd":"ga\u00e9lico escoc\u00e9s","gl":"galego","gn":"guaran\u00ed","gu":"guxaratiano","gv":"manx","ha":"hausa","he":"hebreo","hi":"hindi","hr":"croata","ht":"haitiano","hu":"h\u00fangaro","hy":"armenio","ia":"interlingua","id":"indonesio","ig":"ibo","ii":"yi sichuan\u00e9s","is":"island\u00e9s","it":"italiano","iu":"inuit","ja":"xapon\u00e9s","jv":"xavan\u00e9s","ka":"xeorxiano","kg":"kongo","ki":"kikuyu","kk":"casaco","kl":"groenland\u00e9s","km":"cambodiano","kn":"kannada","ko":"coreano","ks":"cachemir","ku":"kurdo","kw":"c\u00f3rnico","ky":"quirguiz","la":"lat\u00edn","lb":"luxemburgu\u00e9s","lg":"ganda","ln":"lingala","lo":"laotiano","lt":"lituano","lu":"luba-katanga","lv":"let\u00f3n","mg":"malgaxe","mi":"maor\u00ed","mk":"macedonio","ml":"malabar","mn":"mongol","mr":"marathi","ms":"malaio","mt":"malt\u00e9s","my":"birmano","nb":"noruegu\u00e9s bokmal","nd":"ndebele do norte","ne":"nepal\u00ed","nl":"holand\u00e9s","nl_BE":"flamenco","nn":"noruegu\u00e9s nynorsk","no":"noruegu\u00e9s","ny":"chewa","oc":"occitano","om":"oromo","or":"oriya","os":"osetio","pa":"punjabi","pl":"polaco","ps":"paxt\u00fan","pt":"portugu\u00e9s","pt_BR":"portugu\u00e9s brasileiro","pt_PT":"portugu\u00e9s europeo","qu":"quechua","rm":"romanche","rn":"rundi","ro":"roman\u00e9s","ro_MD":"roman\u00e9s moldavo","ru":"ruso","rw":"ruand\u00e9s","sa":"s\u00e1nscrito","sd":"sindhi","se":"sami do norte","sg":"sango","sh":"serbocroata","si":"cingal\u00e9s","sk":"eslovaco","sl":"esloveno","sm":"samoano","sn":"shona","so":"somal\u00ed","sq":"alban\u00e9s","sr":"serbio","ss":"swati","st":"sesoto","su":"sondan\u00e9s","sv":"sueco","sw":"swahili","ta":"tamil","te":"telugu","tg":"taxico","th":"tailand\u00e9s","ti":"tigri\u00f1a","tk":"turcomano","tl":"tagalo","tn":"tswana","to":"tongan\u00e9s","tr":"turco","ts":"xitsonga","tt":"t\u00e1rtaro","tw":"twi","ty":"tahitiano","ug":"uigur","uk":"ucra\u00edno","ur":"urd\u00fa","uz":"uzbeco","ve":"venda","vi":"vietnamita","wo":"w\u00f3lof","xh":"xhosa","yi":"yiddish","yo":"ioruba","zh":"chin\u00e9s","zu":"zul\u00fa"}